retroarcher/__init__.py
retroarcher/games.py
retroarcher/main.py
retroarcher/render.py
retroarcher/settings.py
retroarcher-0.2.1.dist-info/entry_points.txt
retroarcher-0.2.1.dist-info/WHEEL
retroarcher-0.2.1.dist-info/METADATA
retroarcher-0.2.1.dist-info/RECORD
