Metadata-Version: 2.1
Name: retroarcher
Version: 0.2.1
Summary: Generates playlists and remap files for RetroArch.
Author: Tim Simpson
Author-email: timsimpson4@gmail.com
Requires-Python: >=3.6,<4.0
Classifier: Programming Language :: Python :: 3
Classifier: Programming Language :: Python :: 3.6
Classifier: Programming Language :: Python :: 3.7
Classifier: Programming Language :: Python :: 3.8
Requires-Dist: typing-extensions (>=3.7.4,<4.0.0)
